textsynth/__init__.py
textsynth/client.py
textsynth/engine.py
textsynth-0.2.1.dist-info/LICENSE
textsynth-0.2.1.dist-info/METADATA
textsynth-0.2.1.dist-info/WHEEL
textsynth-0.2.1.dist-info/top_level.txt
textsynth-0.2.1.dist-info/RECORD
